{"Month":10,"Year":2025,"DaysData":[{"Date":"2025/10/01","Type":"poem ","Title":null,"Link":"poems/01.10.25.html"},{"Date":"2025/10/02","Type":"poem ","Title":null,"Link":"poems/02.10.25.html"},{"Date":"2025/10/03","Type":"poem ","Title":null,"Link":"poems/03.10.25.html"},{"Date":"2025/10/04","Type":"poem ","Title":null,"Link":"poems/04.10.25.html"},{"Date":"2025/10/05","Type":"poem ","Title":null,"Link":"poems/05.10.25.html"},{"Date":"2025/10/06","Type":"poem ","Title":null,"Link":"poems/06.10.25.html"},{"Date":"2025/10/07","Type":"poem ","Title":null,"Link":"poems/07.10.25.html"}],"MinYear":2004}